Workbook

Sheet Manufacturing Information
A1: employer_name | B1: job_title | C1: salary_raw | D1: salary_min | E1: salary_max | F1: platform | G1: position_link | H1: career_website
A2: Tesla | B2: Internship, Controls Engineer, Manufacturing (Fall 2025) | C2: null | D2: null | E2: null | F2: Handshake | G2: N/A | H2: Tesla Careers
A3: Tesla | B3: Internship, Equipment Engineer, Manufacturing (Winter/Spring 2026) | C3: null | D3: null | E3: null | F3: Handshake | G3: N/A | H3: Tesla Careers
A4: Tesla | B4: Internship, Construction Project Management, Infrastructure (Fall 2025) | C4: null | D4: null | E4: null | F4: Handshake | G4: N/A | H4: Tesla Careers
A5: Tesla | B5: Internship, 3D Generalist, Vehicle User Interface (Summer 2025) | C5: null | D5: null | E5: null | F5: Handshake | G5: N/A | H5: Tesla Careers
A6: Tesla | B6: Sr. Industrial Engineer | C6: null | D6: null | E6: null | F6: Handshake | G6: N/A | H6: Tesla Careers
A7: Tesla | B7: Internship, IT Operations Intern, Infrastructure Engineering (Fall 2025) | C7: null | D7: null | E7: null | F7: Handshake | G7: N/A | H7: Tesla Careers
A8: Tesla | B8: Internship, Security Services Coordinator, Security Systems Engineering (Fall 2025) | C8: null | D8: null | E8: null | F8: Handshake | G8: N/A | H8: Tesla Careers
A9: Tesla | B9: Internship, Architecture & Structural Engineer, Infrastructure (Fall 2025) | C9: null | D9: null | E9: null | F9: Handshake | G9: N/A | H9: Tesla Careers
A10: Tesla | B10: Internship, Architecture & Structural Engineer, Infrastructure (Winter/Spring 2026) | C10: null | D10: null | E10: null | F10: Handshake | G10: N/A | H10: Tesla Careers
A11: Tesla | B11: Internship, Software Validation Engineer, Vehicle Firmware (Fall 2025) | C11: null | D11: null | E11: null | F11: Handshake | G11: N/A | H11: Tesla Careers
A12: Tesla | B12: Entry Level Chemical Operator | C12: null | D12: null | E12: null | F12: Handshake | G12: N/A | H12: Tesla Careers
... A140: ASML | B140: Quality Engineering Co-Op - Spring 2026 | C140: null | D140: null | E140: null | F140: Handshake | G140: N/A | H140: ASML Careers
A141: Dexcom | B141: Senior Manager of Systems Engineering - Hardware & Firmware | C141: $164,200.00 - $273,600.00 | D141: =TRIM(LEFT($C141, FIND("-", $C141)-1)) -> $164,200.00 | E141: =TRIM(MID($C141, FIND("-", $C141)+1, LEN($C141))) -> $273,600.00 | F141: Website | G141: https://careers.dexcom.com/careers?domain=dexcom.com&start=0&location=San+Diego%2C+CA%2C+United+States&pid=38527152&sort_by=distance&filter_distance=80&filter_include_remote=1 | H141: Dexcom Careers and Job Opportunities
A142: Dexcom | B142: Senior Medical Device Engineer | C142: $105,800.00 - $176,300.00 | D142: =TRIM(LEFT($C142, FIND("-", $C142)-1)) -> $105,800.00 | E142: =TRIM(MID($C142, FIND("-", $C142)+1, LEN($C142))) -> $176,300.00 | F142: Website | G142: https://careers.dexcom.com/careers?domain=dexcom.com&start=0&location=San+Diego%2C+CA%2C+United+States&pid=38528658&sort_by=distance&filter_distance=80&filter_include_remote=1 | H142: Dexcom Careers and Job Opportunities
A143: Dexcom | B143: Product Manager | C143: $122,500.00 - $204,100.00 | D143: =TRIM(LEFT($C143, FIND("-", $C143)-1)) -> $122,500.00 | E143: =TRIM(MID($C143, FIND("-", $C143)+1, LEN($C143))) -> $204,100.00 | F143: Website | G143: https://careers.dexcom.com/careers?domain=dexcom.com&start=0&location=San+Diego%2C+CA%2C+United+States&pid=38600257&sort_by=distance&filter_distance=80&filter_include_remote=1 | H143: Dexcom Careers and Job Opportunities
A144: Dexcom | B144: Sr. Research Scientist, AI Experience (Data Scientist 3) | C144: $116,600.00 - $194,400.00 | D144: =TRIM(LEFT($C144, FIND("-", $C144)-1)) -> $116,600.00 | E144: =TRIM(MID($C144, FIND("-", $C144)+1, LEN($C144))) -> $194,400.00 | F144: Website | G144: https://careers.dexcom.com/careers?domain=dexcom.com&start=0&location=San+Diego%2C+CA%2C+United+States&pid=38634309&sort_by=distance&filter_distance=80&filter_include_remote=1 | H144: Dexcom Careers and Job Opportunities
A145: Dexcom | B145: Commercial Pricing Analyst | C145: $61,900.00 - $103,100.00 | D145: =TRIM(LEFT($C145, FIND("-", $C145)-1)) -> $61,900.00 | E145: =TRIM(MID($C145, FIND("-", $C145)+1, LEN($C145))) -> $103,100.00 | F145: Website | G145: https://careers.dexcom.com/careers?domain=dexcom.com&start=0&location=San+Diego%2C+CA%2C+United+States&pid=38634681&sort_by=distance&filter_distance=80&filter_include_remote=1 | H145: Dexcom Careers and Job Opportunities
A146: Dexcom | B146: Staff Process Engineer | C146: $111,100.00 - $185,100.00 | D146: =TRIM(LEFT($C146, FIND("-", $C146)-1)) -> $111,100.00 | E146: =TRIM(MID($C146, FIND("-", $C146)+1, LEN($C146))) -> $185,100.00 | F146: Website | G146: https://careers.dexcom.com/careers?domain=dexcom.com&start=0&location=San+Diego%2C+CA%2C+United+States&pid=38650202&sort_by=distance&filter_distance=80&filter_include_remote=1 | H146: Dexcom Careers and Job Opportunities
A147: Dexcom | B147: Staff Process Engineer | C147: $111,100.00 - $185,100.00 | D147: =TRIM(LEFT($C147, FIND("-", $C147)-1)) -> $111,100.00 | E147: =TRIM(MID($C147, FIND("-", $C147)+1, LEN($C147))) -> $185,100.00 | F147: Website | G147: https://careers.dexcom.com/careers?domain=dexcom.com&start=0&location=San+Diego%2C+CA%2C+United+States&pid=38650202&sort_by=distance&filter_distance=80&filter_include_remote=1 | H147: Dexcom Careers and Job Opportunities
A148: Dexcom | B148: Director of Medical Device Engineering - Sensor Development | C148: $190,100.00 - $316,800.00 | D148: =TRIM(LEFT($C148, FIND("-", $C148)-1)) -> $190,100.00 | E148: =TRIM(MID($C148, FIND("-", $C148)+1, LEN($C148))) -> $316,800.00 | F148: Website | G148: https://careers.dexcom.com/careers?domain=dexcom.com&start=0&location=San+Diego%2C+CA%2C+United+States&pid=38689354&sort_by=distance&filter_distance=80&filter_include_remote=1 | H148: Dexcom Careers and Job Opportunities
A149: Dexcom | B149: Sr Manager Molding Engineering | C149: $149,000.00 - $248,300.00 | D149: =TRIM(LEFT($C149, FIND("-", $C149)-1)) -> $149,000.00 | E149: =TRIM(MID($C149, FIND("-", $C149)+1, LEN($C149))) -> $248,300.00 | F149: Website | G149: https://careers.dexcom.com/careers?domain=dexcom.com&start=0&location=San+Diego%2C+CA%2C+United+States&pid=38691824&sort_by=distance&filter_distance=80&filter_include_remote=1 | H149: Dexcom Careers and Job Opportunities
A150: Dexcom | B150: Principal Engineer - Head of Sensor Production Support | C150: $181,000.00 - $301,600.00 | D150: =TRIM(LEFT($C150, FIND("-", $C150)-1)) -> $181,000.00 | E150: =TRIM(MID($C150, FIND("-", $C150)+1, LEN($C150))) -> $301,600.00 | F150: Website | G150: https://careers.dexcom.com/careers?domain=dexcom.com&start=0&location=San+Diego%2C+CA%2C+United+States&pid=38067926&sort_by=distance&filter_distance=80&filter_include_remote=1 | H150: Dexcom Careers and Job Opportunities
A151: Dexcom | B151: Senior Staff Systems Engineer | C151: $149,000.00 - $248,300.00 | D151: =TRIM(LEFT($C151, FIND("-", $C151)-1)) -> $149,000.00 | E151: =TRIM(MID($C151, FIND("-", $C151)+1, LEN($C151))) -> $248,300.00 | F151: Website | G151: https://careers.dexcom.com/careers?domain=dexcom.com&start=0&location=San+Diego%2C+CA%2C+United+States&pid=38258935&sort_by=distance&filter_distance=80&filter_include_remote=1 | H151: Dexcom Careers and Job Opportunities
A152: Dexcom | B152: Senior Systems Engineer - Hardware Platforms | C152: $111,100.00 - $185,100.00 | D152: =TRIM(LEFT($C152, FIND("-", $C152)-1)) -> $111,100.00 | E152: =TRIM(MID($C152, FIND("-", $C152)+1, LEN($C152))) -> $185,100.00 | F152: Website | G152: https://careers.dexcom.com/careers?domain=dexcom.com&start=0&location=San+Diego%2C+CA%2C+United+States&pid=38259335&sort_by=distance&filter_distance=80&filter_include_remote=1 | H152: Dexcom Careers and Job Opportunities
... A222: Dexcom | B222: Sr Lead Patient Support Services Analyst | C222: $135,100.00 - $225,100.00 | D222: =TRIM(LEFT($C222, FIND("-", $C222)-1)) -> $135,100.00 | E222: =TRIM(MID($C222, FIND("-", $C222)+1, LEN($C222))) -> $225,100.00 | F222: Website | G222: https://careers.dexcom.com/careers?domain=dexcom.com&start=70&location=San+Diego%2C+CA%2C+United+States&pid=39049356&sort_by=distance&filter_distance=80&filter_include_remote=1 | H222: Dexcom Careers and Job Opportunities
A223: Procter & Gamble | B223: Corporation Aviation Seminar | C223: null | D223: null | E223: null | F223: Website | G223: N/A | H223: P&G Careers
A224: Procter & Gamble | B224: Corporation Aviation Seminar - Seminar | C224: null | D224: null | E224: null | F224: Website | G224: N/A | H224: P&G Careers
A225: Procter & Gamble | B225: Data Scientist | C225: null | D225: null | E225: null | F225: Website | G225: N/A | H225: P&G Careers
A226: Procter & Gamble | B226: Site Digital IT Manager (2026 Grads) | C226: null | D226: null | E226: null | F226: Website | G226: N/A | H226: P&G Careers
A227: Procter & Gamble | B227: Masters Data Science Internship | C227: null | D227: null | E227: null | F227: Website | G227: N/A | H227: P&G Careers
A228: Procter & Gamble | B228: Advanced Analytics & Insights (Consumer & Market Knowledge) Internship - Summer 2026 | C228: null | D228: null | E228: null | F228: Website | G228: N/A | H228: P&G Careers
A229: Procter & Gamble | B229: Analytics & Insights (Consumer & Market Knowledge) Internship - Summer 2026 | C229: null | D229: null | E229: null | F229: Website | G229: N/A | H229: P&G Careers
A230: Procter & Gamble | B230: Sales Internship - Summer 2026 | C230: null | D230: null | E230: null | F230: Website | G230: N/A | H230: P&G Careers
A231: Procter & Gamble | B231: Marketing Technology Intern | C231: null | D231: null | E231: null | F231: Website | G231: N/A | H231: P&G Careers
A232: Procter & Gamble | B232: Site IT Operations Intern | C232: null | D232: null | E232: null | F232: Website | G232: N/A | H232: P&G Careers
A233: Procter & Gamble | B233: Human Resources Internship | C233: null | D233: null | E233: null | F233: Website | G233: N/A | H233: P&G Careers
A234: Procter & Gamble | B234: IT Engineer Internship | C234: null | D234: null | E234: null | F234: Website | G234: N/A | H234: P&G Careers
... A244: Procter & Gamble | B244: Research & Development Engineer Intern | C244: null | D244: null | E244: null | F244: Website | G244: N/A | H244: P&G Careers
A245: Frito-Lay | B245: Sanitor - Part-Time - 1st Shift | C245: 53081.6 | D245: 53081.6 | E245: 53081.6 | F245: Website | G245: https://portal.fritolayemployment.com/fritocareers/JobDetail?jobId=504286&recommendation=&jobName=Sanitor+-+Part-Time+-+1st+Shift&source=&tags= | H245: Frito-Lay Careers
A246: Frito-Lay | B246: Sales Utility Representative | C246: 47944 | D246: 47944 | E246: 47944 | F246: Website | G246: https://portal.fritolayemployment.com/fritocareers/JobDetail?jobId=503836&recommendation=&jobName=Sales+Utility+Representative&source=&tags= | H246: Frito-Lay Careers
A247: Frito-Lay | B247: Route Sales Representative | C247: 70400 | D247: 70400 | E247: 70400 | F247: Website | G247: https://portal.fritolayemployment.com/fritocareers/JobDetail?jobId=505046&recommendation=&jobName=Route+Sales+Representative&source=&tags= | H247: Frito-Lay Careers
A248: Frito-Lay | B248: Route Sales Representative | C248: 70400 | D248: 70400 | E248: 70400 | F248: Website | G248: https://portal.fritolayemployment.com/fritocareers/JobDetail?jobId=504675&recommendation=&jobName=Route+Sales+Representative&source=&tags= | H248: Frito-Lay Careers
A249: Frito-Lay | B249: Route Sales Representative | C249: 70400 | D249: 70400 | E249: 70400 | F249: Website | G249: https://portal.fritolayemployment.com/fritocareers/JobDetail?jobId=504679&recommendation=&jobName=Route+Sales+Representative&source=&tags= | H249: Frito-Lay Careers
A250: Frito-Lay | B250: Route Sales Representative | C250: 70400 | D250: 70400 | E250: 70400 | F250: Website | G250: https://portal.fritolayemployment.com/fritocareers/JobDetail?jobId=504491&recommendation=&jobName=Route+Sales+Representative&source=&tags= | H250: Frito-Lay Careers
A251: Frito-Lay | B251: Sales Utility Representative | C251: 70400 | D251: 70400 | E251: 70400 | F251: Website | G251: https://portal.fritolayemployment.com/fritocareers/JobDetail?jobId=504492&recommendation=&jobName=Route+Sales+Representative&source=&tags= | H251: Frito-Lay Careers
A252: Frito-Lay | B252: Route Sales Representative | C252: 67200 | D252: 67200 | E252: 67200 | F252: Website | G252: https://portal.fritolayemployment.com/fritocareers/JobDetail?jobId=503835&recommendation=&jobName=Route+Sales+Representative&source=&tags= | H252: Frito-Lay Careers
A253: Frito-Lay | B253: Route Sales Representative | C253: 76800 | D253: 76800 | E253: 76800 | F253: Website | G253: https://portal.fritolayemployment.com/fritocareers/JobDetail?jobId=503243&recommendation=&jobName=Route+Sales+Representative&source=&tags= | H253: Frito-Lay Careers
A254: Frito-Lay | B254: Route Sales Representative | C254: 70400 | D254: 70400 | E254: 70400 | F254: Website | G254: https://portal.fritolayemployment.com/fritocareers/JobDetail?jobId=503111&recommendation=&jobName=Route+Sales+Representative&source=&tags= | H254: Frito-Lay Careers
A255: Frito-Lay | B255: Route Sales Representative | C255: 80000 | D255: 80000 | E255: 80000 | F255: Website | G255: https://portal.fritolayemployment.com/fritocareers/JobDetail?jobId=500653&recommendation=&jobName=Route+Sales+Representative&source=&tags= | H255: Frito-Lay Careers
A256: Frito-Lay | B256: Merchandiser - Seasonal | C256: 47944 | D256: 47944 | E256: 47944 | F256: Website | G256: https://portal.fritolayemployment.com/fritocareers/JobDetail?jobId=502986&recommendation=&jobName=Merchandiser+-+Seasonal&source=&tags= | H256: Frito-Lay Careers
... A264: Frito-Lay | B264: Delivery Secialist (No CDL) | C264: 67184 | D264: 67184 | E264: 67184 | F264: Website | G264: https://portal.fritolayemployment.com/fritocareers/JobDetail?jobId=505148&recommendation=&jobName=Delivery+Specialist+%28no+CDL%29&source=&tags= | H264: Frito-Lay Careers
A265: Gusmer Enterprises, Inc. | B265: Safety Coordinator - Part Time | C265: $58,240.00 - $66,560.00 | D265: =TRIM(LEFT($C265, FIND("-", $C265)-1)) -> $58,240.00 | E265: =TRIM(MID($C265, FIND("-", $C265)+1, LEN($C265))) -> $66,560.00 | F265: Website | G265: https://www.gusmerenterprises.com/career/safety-coordinator-part-time/ | H265: Careers | Gusmer Enterprise
A266: Gusmer Enterprises, Inc. | B266: Industrial Maintenance Mechanic | C266: $62,400.00 - $72,800.00 | D266: =TRIM(LEFT($C266, FIND("-", $C266)-1)) -> $62,400.00 | E266: =TRIM(MID($C266, FIND("-", $C266)+1, LEN($C266))) -> $72,800.00 | F266: Website | G266: https://www.gusmerenterprises.com/career/industrial-maintenance-mechanic/ | H266: Careers | Gusmer Enterprise
A267: Gallo Glass Company | B267: Analyst 3 - Supply Chain Buyer | C267: $91,500.00 - $114,400.00 | D267: =TRIM(LEFT($C267, FIND("-", $C267)-1)) -> $91,500.00 | E267: =TRIM(MID($C267, FIND("-", $C267)+1, LEN($C267))) -> $114,400.00 | F267: Website | G267: https://careers.g3enterprises.com/job/Analyst-3-Supply-Chain-Buyer/15237-en_US | H267: Gallo Glass Company Careers (AKA G3 Enterprises)
A268: Gallo Glass Company | B268: Talent Acquisition Partner | C268: $83,200.00 - $104,000.00 | D268: =TRIM(LEFT($C268, FIND("-", $C268)-1)) -> $83,200.00 | E268: =TRIM(MID($C268, FIND("-", $C268)+1, LEN($C268))) -> $104,000.00 | F268: Website | G268: https://careers.g3enterprises.com/job/Talent-Acquisition-Partner/15200-en_US | H268: Gallo Glass Company Careers (AKA G3 Enterprises)
A269: Golden State Foods | B269: Maintenance Mechanic | C269: $63,377.60 - $70,449.60 | D269: =TRIM(LEFT($C269, FIND("-", $C269)-1)) -> $63,377.60 | E269: =TRIM(MID($C269, FIND("-", $C269)+1, LEN($C269))) -> $70,449.60 | F269: Website | G269: https://goldenstatefoods.ttcportals.com/jobs/17026331-maintenance-mechanic | H269: Golden State Foods Careers
A270: Golden State Foods | B270: Warehouse Utility/Yard Driver - 2nd Shift | C270: null | D270: null | E270: null | F270: Website | G270: https://goldenstatefoods.ttcportals.com/jobs/16861813-warehouse-utility-slash-yard-driver | H270: Golden State Foods Careers
A271: Golden State Foods | B271: General Manager | C271: $131,000.00 - $195,000.00 | D271: =TRIM(LEFT($C271, FIND("-", $C271)-1)) -> $131,000.00 | E271: =TRIM(MID($C271, FIND("-", $C271)+1, LEN($C271))) -> $195,000.00 | F271: Website | G271: https://goldenstatefoods.ttcportals.com/jobs/16861813-warehouse-utility-slash-yard-driver | H271: Golden State Foods Careers
A272: Golden State Foods | B272: Sr. Maintenance Supervisor (2nd Shift) | C272: $90,000.00 - $110,000.00 | D272: =TRIM(LEFT($C272, FIND("-", $C272)-1)) -> $90,000.00 | E272: =TRIM(MID($C272, FIND("-", $C272)+1, LEN($C272))) -> $110,000.00 | F272: Website | G272: https://goldenstatefoods.ttcportals.com/jobs/16831365-sr-maintenance-supervisor-2nd-shift | H272: Golden State Foods Careers
A273: Golden State Foods | B273: Sr. Applications Developer Analyst | C273: $125,000.00 - $135,000.00 | D273: =TRIM(LEFT($C273, FIND("-", $C273)-1)) -> $125,000.00 | E273: =TRIM(MID($C273, FIND("-", $C273)+1, LEN($C273))) -> $135,000.00 | F273: Website | G273: https://goldenstatefoods.ttcportals.com/jobs/16432545-sr-applications-developer-analyst | H273: Golden State Foods Careers
A274: California Dairies, Inc. | B274: Relief, Plant Person | C274: 63169.6 | D274: 63169.6 | E274: 63169.6 | F274: Website | G274: https://jobs.dayforcehcm.com/en-US/cadry/CANDIDATEPORTAL/jobs/436 | H274: Careers – California Dairies, Inc.
A275: California Dairies, Inc. | B275: Sanitation | C275: 54600 | D275: 54600 | E275: 54600 | F275: Website | G275: https://jobs.dayforcehcm.com/en-US/cadry/CANDIDATEPORTAL/jobs/432 | H275: Careers – California Dairies, Inc.
A276: California Dairies, Inc. | B276: Supervisor, Warehouse | C276: $72,499.00 - $107,769.00 | D276: =TRIM(LEFT($C276, FIND("-", $C276)-1)) -> $72,499.00 | E276: =TRIM(MID($C276, FIND("-", $C276)+1, LEN($C276))) -> $107,769.00 | F276: Website | G276: https://jobs.dayforcehcm.com/en-US/cadry/CANDIDATEPORTAL/jobs/408 | H276: Careers – California Dairies, Inc.
A277: California Dairies, Inc. | B277: Maintenance Supervisor | C277: $79,608.00 - $118,336.00 | D277: =TRIM(LEFT($C277, FIND("-", $C277)-1)) -> $79,608.00 | E277: =TRIM(MID($C277, FIND("-", $C277)+1, LEN($C277))) -> $118,336.00 | F277: Website | G277: https://jobs.dayforcehcm.com/en-US/cadry/CANDIDATEPORTAL/jobs/326 | H277: Careers – California Dairies, Inc.
A278: California Dairies, Inc. | B278: Plant Manager, Processing & Powder | C278: $104,802.00 - $160,114.00 | D278: =TRIM(LEFT($C278, FIND("-", $C278)-1)) -> $104,802.00 | E278: =TRIM(MID($C278, FIND("-", $C278)+1, LEN($C278))) -> $160,114.00 | F278: Website | G278: https://jobs.dayforcehcm.com/en-US/cadry/CANDIDATEPORTAL/jobs/279 | H278: Careers – California Dairies, Inc.
A279: California Dairies, Inc. | B279: Maintenance Mechanic - Turlock South | C279: null | D279: null | E279: null | F279: Website | G279: https://jobs.dayforcehcm.com/en-US/cadry/CANDIDATEPORTAL/jobs/246 | H279: Careers – California Dairies, Inc.
A280: California Dairies, Inc. | B280: Supervisor, Maintenance | C280: $79,608.00 - $118,336.00 | D280: =TRIM(LEFT($C280, FIND("-", $C280)-1)) -> $79,608.00 | E280: =TRIM(MID($C280, FIND("-", $C280)+1, LEN($C280))) -> $118,336.00 | F280: Website | G280: https://jobs.dayforcehcm.com/en-US/cadry/CANDIDATEPORTAL/jobs/242 | H280: Careers – California Dairies, Inc.
A281: California Dairies, Inc. | B281: Continuous Improvement Manager | C281: $84,533.00 - $126,512.00 | D281: =TRIM(LEFT($C281, FIND("-", $C281)-1)) -> $84,533.00 | E281: =TRIM(MID($C281, FIND("-", $C281)+1, LEN($C281))) -> $126,512.00 | F281: Website | G281: https://jobs.dayforcehcm.com/en-US/cadry/CANDIDATEPORTAL/jobs/70 | H281: Careers – California Dairies, Inc.
A282: GrayMatter Robotics | B282: Robotics Engineer: System and Applications | C282: $115,000.00 - $150,000.00 | D282: =TRIM(LEFT($C282, FIND("-", $C282)-1)) -> $115,000.00 | E282: =TRIM(MID($C282, FIND("-", $C282)+1, LEN($C282))) -> $150,000.00 | F282: Website | G282: https://jobs.ashbyhq.com/graymatter-robotics/d641a19c-c877-49b4-8740-a7fbb6c86888 | H282: GrayMatter Robotics Jobs
A283: GrayMatter Robotics | B283: Robotics Engineer: System and Applications, New Grad | C283: $90,000.00 - $115,000.00 | D283: =TRIM(LEFT($C283, FIND("-", $C283)-1)) -> $90,000.00 | E283: =TRIM(MID($C283, FIND("-", $C283)+1, LEN($C283))) -> $115,000.00 | F283: Website | G283: https://jobs.ashbyhq.com/graymatter-robotics/0d819d81-9013-485c-b3b2-b2253621ad8c | H283: GrayMatter Robotics Jobs
A284: GrayMatter Robotics | B284: Robotics Engineering Intern: Systems & Applications | C284: $62,400.00 - $83,200.00 | D284: =TRIM(LEFT($C284, FIND("-", $C284)-1)) -> $62,400.00 | E284: =TRIM(MID($C284, FIND("-", $C284)+1, LEN($C284))) -> $83,200.00 | F284: Website | G284: https://jobs.ashbyhq.com/graymatter-robotics/b3ccaee6-9c32-428f-aba6-2819e3c1d9d6 | H284: GrayMatter Robotics Jobs
A285: GrayMatter Robotics | B285: Robotics Engineering Manager: Systems & Applications | C285: $200,000.00 - $220,000.00 | D285: =TRIM(LEFT($C285, FIND("-", $C285)-1)) -> $200,000.00 | E285: =TRIM(MID($C285, FIND("-", $C285)+1, LEN($C285))) -> $220,000.00 | F285: Website | G285: https://jobs.ashbyhq.com/graymatter-robotics/b17273ca-66a1-4e6c-968a-79ae9b71f4c1 | H285: GrayMatter Robotics Jobs
A286: GrayMatter Robotics | B286: Office Administrator | C286: $41,600.00 - $62,400.00 | D286: =TRIM(LEFT($C286, FIND("-", $C286)-1)) -> $41,600.00 | E286: =TRIM(MID($C286, FIND("-", $C286)+1, LEN($C286))) -> $62,400.00 | F286: Website | G286: https://jobs.ashbyhq.com/graymatter-robotics/4e46049a-a261-4f17-9ca3-b1d50c19f169 | H286: GrayMatter Robotics Jobs
A287: GrayMatter Robotics | B287: Warehouse Facilities Manager | C287: $110,000.00 - $145,000.00 | D287: =TRIM(LEFT($C287, FIND("-", $C287)-1)) -> $110,000.00 | E287: =TRIM(MID($C287, FIND("-", $C287)+1, LEN($C287))) -> $145,000.00 | F287: Website | G287: https://jobs.ashbyhq.com/graymatter-robotics/dc45a3bc-05df-4625-841b-b2da4b658111 | H287: GrayMatter Robotics Jobs
A288: GrayMatter Robotics | B288: Robotics Engineer: Software, New Grad | C288: $100,000.00 - $120,000.00 | D288: =TRIM(LEFT($C288, FIND("-", $C288)-1)) -> $100,000.00 | E288: =TRIM(MID($C288, FIND("-", $C288)+1, LEN($C288))) -> $120,000.00 | F288: Website | G288: https://jobs.ashbyhq.com/graymatter-robotics/9c82239a-1480-47db-9f5c-4113e829232c | H288: GrayMatter Robotics Jobs
A289: GrayMatter Robotics | B289: Robotics Engineer: Systems & Applications | C289: $90,000.00 - $115,000.00 | D289: =TRIM(LEFT($C289, FIND("-", $C289)-1)) -> $90,000.00 | E289: =TRIM(MID($C289, FIND("-", $C289)+1, LEN($C289))) -> $115,000.00 | F289: Website | G289: https://jobs.ashbyhq.com/graymatter-robotics/33f2fffb-c16c-4714-836b-5c845879efe6 | H289: GrayMatter Robotics Jobs
A290: GrayMatter Robotics | B290: Robotics Engineering Intern: Software | C290: $72,800.00 - $93,600.00 | D290: =TRIM(LEFT($C290, FIND("-", $C290)-1)) -> $72,800.00 | E290: =TRIM(MID($C290, FIND("-", $C290)+1, LEN($C290))) -> $93,600.00 | F290: Website | G290: https://jobs.ashbyhq.com/graymatter-robotics/adf6d70d-df0a-4966-843b-614cb5038d01 | H290: GrayMatter Robotics Jobs
A291: GrayMatter Robotics | B291: Robotics Engineering Intern: Systems & Applications | C291: $62,400.00 - $83,200.00 | D291: =TRIM(LEFT($C291, FIND("-", $C291)-1)) -> $62,400.00 | E291: =TRIM(MID($C291, FIND("-", $C291)+1, LEN($C291))) -> $83,200.00 | F291: Website | G291: https://jobs.ashbyhq.com/graymatter-robotics/245b7097-9909-4fee-82c8-b9f0acf03f87 | H291: GrayMatter Robotics Jobs
... A302: Stanislaus Food Products Co. | B302: Seasonal Safety Clerk | C302: $45,240.00 - $46,800.00 | D302: =TRIM(LEFT($C302, FIND("-", $C302)-1)) -> $45,240.00 | E302: =TRIM(MID($C302, FIND("-", $C302)+1, LEN($C302))) -> $46,800.00 | F302: Website | G302: https://recruiting2.ultipro.com/STA1045STAFP/JobBoard/647cb3f9-edae-414e-a5fe-c4a67c86dd6a/OpportunityDetail?opportunityId=c4269281-a065-4adf-9f2d-fbec5f5b502d | H302: Stanislaus Food Products Careers
A303: Stanislaus Food Products Co. | B303: Electrician | C303: 81203.2 | D303: 81203.2 | E303: 81203.2 | F303: Website | G303: https://recruiting2.ultipro.com/STA1045STAFP/JobBoard/647cb3f9-edae-414e-a5fe-c4a67c86dd6a/OpportunityDetail?opportunityId=3a762350-0c20-459d-bf34-717490dd5c75 | H303: Stanislaus Food Products Careers
A304: Stanislaus Food Products Co. | B304: System Administrator | C304: $95,000.00 - $120,000.00 | D304: =TRIM(LEFT($C304, FIND("-", $C304)-1)) -> $95,000.00 | E304: =TRIM(MID($C304, FIND("-", $C304)+1, LEN($C304))) -> $120,000.00 | F304: Website | G304: https://recruiting2.ultipro.com/STA1045STAFP/JobBoard/647cb3f9-edae-414e-a5fe-c4a67c86dd6a/OpportunityDetail?opportunityId=823979e6-a53b-4147-bb34-5e4eafb07790 | H304: Stanislaus Food Products Careers
A305: Stanislaus Food Products Co. | B305: Business Development Representative - Northern Virginia | C305: 60000 | D305: 60000 | E305: 60000 | F305: Website | G305: https://recruiting2.ultipro.com/STA1045STAFP/JobBoard/647cb3f9-edae-414e-a5fe-c4a67c86dd6a/OpportunityDetail?opportunityId=39b5264d-ccbf-40dc-a9cf-594781ca045d | H305: Stanislaus Food Products Careers
A306: Kaiser Aluminum | B306: Maintenance Supervisor | C306: null | D306: null | E306: null | F306: Website | G306: https://myjobs.adp.com/kaisercareers/cx/job-listing?FIELD1=California | H306: Kaiser Aluminum Careers
A307: Kaiser Aluminum | B307: Continuous Improvement Manager | C307: $150,000.00 - $180,000.00 | D307: =TRIM(LEFT($C307, FIND("-", $C307)-1)) -> $150,000.00 | E307: =TRIM(MID($C307, FIND("-", $C307)+1, LEN($C307))) -> $180,000.00 | F307: Website | G307: https://myjobs.adp.com/kaisercareers/cx/job-listing?FIELD1=California | H307: Kaiser Aluminum Careers
A308: Kaiser Aluminum | B308: Master-Master Maintenance Technician | C308: 83200 | D308: 83200 | E308: 83200 | F308: Website | G308: https://myjobs.adp.com/kaisercareers/cx/job-listing?FIELD1=California | H308: Kaiser Aluminum Careers
A309: Boeing | B309: Lead Manufacturing Engineer | C309: $129,200.00 - $174,800.00 | D309: =TRIM(LEFT($C309, FIND("-", $C309)-1)) -> $129,200.00 | E309: =TRIM(MID($C309, FIND("-", $C309)+1, LEN($C309))) -> $174,800.00 | F309: Website | G309: https://jobs.boeing.com/job/los-angeles/lead-manufacturing-engineer/185/89064253888 | H309: Boeing Careers
A310: Boeing | B310: Systems Engineer Lead | C310: $138,550.00 - $187,450.00 | D310: =TRIM(LEFT($C310, FIND("-", $C310)-1)) -> $138,550.00 | E310: =TRIM(MID($C310, FIND("-", $C310)+1, LEN($C310))) -> $187,450.00 | F310: Website | G310: https://jobs.boeing.com/job/los-angeles/systems-engineer-lead-or-senior/185/88882208608 | H310: Boeing Careers
A311: Boeing | B311: Systems Engineer Senior | C311: $165,750.00 - $224,250.00 | D311: =TRIM(LEFT($C311, FIND("-", $C311)-1)) -> $165,750.00 | E311: =TRIM(MID($C311, FIND("-", $C311)+1, LEN($C311))) -> $224,250.00 | F311: Website | G311: https://jobs.boeing.com/job/los-angeles/systems-engineer-lead-or-senior/185/88882208608 | H311: Boeing Careers
A312: Boeing | B312: Space Communications Payload Systems Engineer Lead | C312: $138,550.00 - $187,450.00 | D312: =TRIM(LEFT($C312, FIND("-", $C312)-1)) -> $138,550.00 | E312: =TRIM(MID($C312, FIND("-", $C312)+1, LEN($C312))) -> $187,450.00 | F312: Website | G312: https://jobs.boeing.com/job/los-angeles/space-communications-payload-systems-engineer-lead-or-senior/185/88882208560 | H312: Boeing Careers
A313: Boeing | B313: Space Communications Payload Systems Engineer Senior | C313: $165,750.00 - $224,250.00 | D313: =TRIM(LEFT($C313, FIND("-", $C313)-1)) -> $165,750.00 | E313: =TRIM(MID($C313, FIND("-", $C313)+1, LEN($C313))) -> $224,250.00 | F313: Website | G313: https://jobs.boeing.com/job/los-angeles/space-communications-payload-systems-engineer-lead-or-senior/185/88882208560 | H313: Boeing Careers
A314: Boeing | B314: ASIC/FPGA Design Engineering Manager | C314: $141,100.00 - $190,900.00 | D314: =TRIM(LEFT($C314, FIND("-", $C314)-1)) -> $141,100.00 | E314: =TRIM(MID($C314, FIND("-", $C314)+1, LEN($C314))) -> $190,900.00 | F314: Website | G314: https://jobs.boeing.com/job/los-angeles/asic-fpga-design-engineering-manager/185/88873270256 | H314: Boeing Careers
A315: Boeing | B315: Associate Manufacturing Engineer - Electrical | C315: $89,250.00 - $120,750.00 | D315: =TRIM(LEFT($C315, FIND("-", $C315)-1)) -> $89,250.00 | E315: =TRIM(MID($C315, FIND("-", $C315)+1, LEN($C315))) -> $120,750.00 | F315: Website | G315: https://jobs.boeing.com/job/los-angeles/associate-manufacturing-engineer-electrical/185/88873255536 | H315: Boeing Careers
A316: Boeing | B316: Production Control Support (Materials Management)-2 | C316: $73,100.00 - $90,300.00 | D316: =TRIM(LEFT($C316, FIND("-", $C316)-1)) -> $73,100.00 | E316: =TRIM(MID($C316, FIND("-", $C316)+1, LEN($C316))) -> $90,300.00 | F316: Website | G316: https://jobs.boeing.com/job/los-angeles/production-control-support-materials-management-2/185/88836294064 | H316: Boeing Careers
A317: Boeing | B317: Labor Relations Specialist Experienced | C317: $96,050.00 - $129,950.00 | D317: =TRIM(LEFT($C317, FIND("-", $C317)-1)) -> $96,050.00 | E317: =TRIM(MID($C317, FIND("-", $C317)+1, LEN($C317))) -> $129,950.00 | F317: Website | G317: https://jobs.boeing.com/job/los-angeles/labor-relations-specialist-experienced-or-senior/185/88699480320 | H317: Boeing Careers
A318: Boeing | B318: Labor Relations Specialist Senior | C318: $119,000.00 - $161,000.00 | D318: =TRIM(LEFT($C318, FIND("-", $C318)-1)) -> $119,000.00 | E318: =TRIM(MID($C318, FIND("-", $C318)+1, LEN($C318))) -> $161,000.00 | F318: Website | G318: https://jobs.boeing.com/job/los-angeles/labor-relations-specialist-experienced-or-senior/185/88699480320 | H318: Boeing Careers
A319: Boeing | B319: Senior Business Operations Lead Level 4 | C319: $120,700.00 - $163,300.00 | D319: =TRIM(LEFT($C319, FIND("-", $C319)-1)) -> $120,700.00 | E319: =TRIM(MID($C319, FIND("-", $C319)+1, LEN($C319))) -> $163,300.00 | F319: Website | G319: https://jobs.boeing.com/job/los-angeles/senior-business-operations-lead/185/88649527968 | H319: Boeing Careers
A320: Boeing | B320: Senior Business Operations Lead Level 5 | C320: $151,300.00 - $204,700.00 | D320: =TRIM(LEFT($C320, FIND("-", $C320)-1)) -> $151,300.00 | E320: =TRIM(MID($C320, FIND("-", $C320)+1, LEN($C320))) -> $204,700.00 | F320: Website | G320: https://jobs.boeing.com/job/los-angeles/senior-business-operations-lead/185/88649527968 | H320: Boeing Careers
... A425: Boeing | B425: Experienced Contracts Paralegal | C425: $107,100.00 - $155,250.00 | D425: =TRIM(LEFT($C425, FIND("-", $C425)-1)) -> $107,100.00 | E425: =TRIM(MID($C425, FIND("-", $C425)+1, LEN($C425))) -> $155,250.00 | F425: Website | G425: https://jobs.boeing.com/job/seattle/experienced-contracts-paralegal/185/88429716320 | H425: Boeing Careers
A426: Boeing | B426: Product Review Engineer | C426: 142355 | D426: 142355 | E426: 142355 | F426: Website | G426: https://jobs.boeing.com/job/seal-beach/product-review-engineer/185/88118333248 | H426: Boeing Careers
...

Sheet Additional Notes + Log
B1: 45992 | C1: Monday Day 1 | D1: Notes
A2: Number of Postings | B2: Company Name | D2: All provided active job postings are in the last 12 months
A3: =COUNTIF('Manufacturing Information'!A:A, $B3) -> 61 | B3: Tesla | C3: Complete | D3: Handshake companies, including Tesla, ResMed, Oldcastle Infrastructure, General Atomics, and ASML, had not provided salaries in their postings
A4: =COUNTIF('Manufacturing Information'!A:A, $B4) -> 18 | B4: ResMed | C4: Complete
A5: =COUNTIF('Manufacturing Information'!A:A, $B5) -> 12 | B5: Oldcastle Infrastructure | C5: Complete
A6: =COUNTIF('Manufacturing Information'!A:A, $B6) -> 7 | B6: General Atomics | C6: Complete
A7: =COUNTIF('Manufacturing Information'!A:A, $B7) -> 41 | B7: ASML | C7: Complete
A8: =COUNTIF('Manufacturing Information'!A:A, $B8) -> 22 | B8: Procter & Gamble | C8: Complete | D8: Tesla, ResMed, Oldcastyle, General Atomics, ASML showed up in Handshake Report Filtering, Procter & Gamble did not but had Handshake listings
A9: =COUNTIF('Manufacturing Information'!A:A, $B9) -> 82 | B9: Dexcom | C9: Complete | D9: None posted on Handshake, posted on website, the following companies for day 2 will be all through website
A10: TODAY TOTAL
A11: =SUM(A3:A9) -> 243
B12: 45993 | C12: Tuesday Day 2 | D12: Notes
A13: =COUNTIF('Manufacturing Information'!A:A, $B13) -> 20 | B13: Frito-Lay | C13: Complete | D13: For some, hourly wage was given, salary was calculated by hourly wage * 2080 hours to simulate an annual salary assuming a standard 40 hour work week
A14: =COUNTIF('Manufacturing Information'!A:A, $B14) -> 0 | B14: LiDestri Food & Drink | C14: Complete | D14: https://lidestrifoods.com/careers None listed in Fresno
A15: =COUNTIF('Manufacturing Information'!A:A, $B15) -> 0 | B15: Busseto Foods, Inc. | C15: Complete | D15: https://busseto.com/careers/career-opportunities has no listings
A16: =COUNTIF('Manufacturing Information'!A:A, $B16) -> 2 | B16: Gusmer Enterprises, Inc. | C16: Complete
A17: =COUNTIF('Manufacturing Information'!A:A, $B17) -> 135 | B17: Boeing | C17: Complete | D17: https://jobs.boeing.com/search-jobs/Los%20Angeles%2C%20CA/185/4/6252001-5332921-5368381-5368361/34x05223/-118x24368/50/2 87
A18: =COUNTIF('Manufacturing Information'!A:A, $B18) -> 0 | B18: RCM Industries | C18: Complete | D18: https://www.paycomonline.net/v4/ats/web.php/jobs None listed in Los Angeles region
A19: =COUNTIF('Manufacturing Information'!A:A, $B19) -> 3 | B19: Kaiser Aluminum | C19: Complete
A20: =COUNTIF('Manufacturing Information'!A:A, $B20) -> 0 | B20: Spreckels Sugar Co., Inc. | C20: Complete | D20: https://recruiting2.ultipro.com/SOU1047SMBSC/JobBoard/660f759a-4cc9-435c-bbe9-4bf35aecfda4/?q=&o=postedDateDesc 0 opportunities available
A21: =COUNTIF('Manufacturing Information'!A:A, $B21) -> 0 | B21: Statevolt | C21: Complete | D21: https://statevolt.com/careers/ would have to contact a Statevolt representative to find current openings and application process
A22: =COUNTIF('Manufacturing Information'!A:A, $B22) -> 0 | B22: Rayotek Scientific, Inc. | C22: Complete | D22: https://www.linkedin.com/company/rayotek-scientific-llc/jobs/ no jobs posted
A23: =COUNTIF('Manufacturing Information'!A:A, $B23) -> 0 | B23: Tolar Manufacturing Company | C23: Complete | D23: https://tolarmfg.com/who-we-are/work-for-us/ any open positions aren't listed
A24: =COUNTIF('Manufacturing Information'!A:A, $B24) -> 5 | B24: Stanislaus Food Products Co. | C24: Complete
A25: =COUNTIF('Manufacturing Information'!A:A, $B25) -> 0 | B25: Plum Organics | C25: Complete | D25: https://www.plumorganics.com/?s=careers no results found
A26: =COUNTIF('Manufacturing Information'!A:A, $B26) -> 0 | B26: Fast Trak Fabrication | C26: Complete | D26: None found
A27: =COUNTIF('Manufacturing Information'!A:A, $B27) -> 19 | B27: GrayMatter Robotics | C27: Complete | D27: 19 https://jobs.ashbyhq.com/graymatter-robotics
A28: =COUNTIF('Manufacturing Information'!A:A, $B28) -> 2 | B28: Gallo Glass Company | C28: Complete
A29: =COUNTIF('Manufacturing Information'!A:A, $B29) -> 8 | B29: California Dairies, Inc. | C29: Complete
A30: =COUNTIF('Manufacturing Information'!A:A, $B30) -> 5 | B30: Golden State Foods | C30: Complete
A31: TODAY TOTAL
A32: =SUM(A13:A31) -> 199
A33: For reproducibility and workflow, Additional Notes + Log was added for explanations, Data Dictionary for understanding variables, and calculated salary if given hourly wage
A34: TOTAL TOTAL
A35: =COUNTA('Manufacturing Information'!A:A) -> 443

Sheet Data Dictionary
A1: Name of Variable | B1: Description | C1: Type
A2: employer_name | B2: The name of the employer | C2: String
A3: job_title | B3: The job title | C3: String
A4: salary_raw | B4: The provided (or calculated) salary in the posting if applicable; for data science purposes, we won't be using this column; it is purely informational | C4: $, double
A5: salary_min | B5: The provided (or calculated) salary lowest end range, or if the salary is a fixed number, then this is where that value goes | C5: $, double
A6: salary_max | B6: The provided (or calculated) salary highest end range; this column is only helpful if salary_min is not equal to salary_max, since this is for ranges, not a fixed salary | C6: $, double
A7: platform | B7: If this information was provided by either Handshake or directly from the careers website | C7: String
A8: position_link | B8: Link to job posting (if applicable) for reference | C8: String
A9: career_website | B9: Link to employers careers website | C9: String

Sheet Calculated Salary (If Hourly Wa
A1: References
A2: Position in Sheet 1 | B2: Hourly Wage | C2: Salary End | D2: Calculation Cell | E2: Usable
A3: 245 | B3: 25.52 | C3: Min/Max | D3: =$B3*2080 -> 53081.6 | E3: 53081
A4: 246 | B4: 23.05 | C4: Min/Max | D4: =$B4*2080 -> 47944 | E4: 47944
A5: 256 | B5: 24 | C5: Min/Max | D5: =$B5*2080 -> 49920 | E5: 47944
A6: 257 | B6: 26.2 | C6: Min/Max | D6: =$B6*2080 -> 54496 | E6: 54496
A7: 258 | B7: 24 | C7: Min/Max | D7: =$B7*2080 -> 49920 | E7: 47944
A8: 259 | B8: 25.4 | C8: Min/Max | D8: =$B8*2080 -> 52832 | E8: 52832
A9: 260 | B9: 24.36 | C9: Min/Max | D9: =$B9*2080 -> 50668.8 | E9: 50668.8
A10: 261 | B10: 19.5 | C10: Min/Max | D10: =$B10*2080 -> 40560 | E10: 40560
A11: 262 | B11: 19.1 | C11: Min/Max | D11: =$B11*2080 -> 39728 | E11: 39728
A12: 263 | B12: 18.45 | C12: Min/Max | D12: =$B12*2080 -> 38376 | E12: 38376
A13: 264 | B13: 32.3 | C13: Min/Max | D13: =$B13*2080 -> 67184 | E13: 67184
A14: 265 | B14: 28 | C14: Min | D14: =$B14*2080 -> 58240 | E14: 58240
B15: 32 | C15: Max | D15: =$B15*2080 -> 66560 | E15: 66560
A16: 266 | B16: 30 | C16: Min | D16: =$B16*2080 -> 62400 | E16: 62400
B17: 35 | C17: Max | D17: =$B17*2080 -> 72800 | E17: 72800
A18: 269 | B18: 30.47 | C18: Min | D18: =$B18*2080 -> 63377.6 | E18: 63377.6
B19: 33.87 | C19: Max | D19: =$B19*2080 -> 70449.6 | E19: 70449.6
A20: 274 | B20: 30.37 | C20: Min/Max | D20: =$B20*2080 -> 63169.6 | E20: 63169.6
A21: 275 | B21: 26.25 | C21: Min/Max | D21: =$B21*2080 -> 54600 | E21: 54600
A22: 284 | B22: 30 | C22: Min | D22: =$B22*2080 -> 62400 | E22: 62400
B23: 40 | C23: Max | D23: =$B23*2080 -> 83200 | E23: 83200
A24: 286 | B24: 20 | C24: Min | D24: =$B24*2080 -> 41600 | E24: 41600
B25: 30 | C25: Max | D25: =$B25*2080 -> 62400 | E25: 62400
A26: 290 | B26: 35 | C26: Min | D26: =$B26*2080 -> 72800 | E26: 72800
B27: 45 | C27: Max | D27: =$B27*2080 -> 93600 | E27: 93600
A28: 291 | B28: 30 | C28: Min | D28: =$B28*2080 -> 62400 | E28: 62400
B29: 40 | C29: Max | D29: =$B29*2080 -> 83200 | E29: 83200
A30: 299 | B30: 35 | C30: Min | D30: =$B30*2080 -> 72800 | E30: 72800
B31: 45 | C31: Max | D31: =$B31*2080 -> 93600 | E31: 93600
A32: 302 | B32: 21.75 | C32: Min | D32: =$B32*2080 -> 45240 | E32: 45240
B33: 22.5 | C33: Max | D33: =$B33*2080 -> 46800 | E33: 46800
A34: 303 | B34: 39.04 | C34: Min/Max | D34: =$B34*2080 -> 81203.2 | E34: 81203.2
A35: 308 | B35: 40 | C35: Min/Max | D35: =$B35*2080 -> 83200 | E35: 83200
